{
  "english_words": [
    {
      "word": "implement",
      "pos": "v.",
      "meaning": "執行、實施（計畫或政策）",
      "example": "We need to implement the new security features next week.",
      "example_zh": "我們下週需要實施新的安全功能。"
    },
    {
      "word": "optimize",
      "pos": "v.",
      "meaning": "優化、最佳化（系統或流程）",
      "example": "Can we optimize this code for better performance?",
      "example_zh": "我們可以優化這段程式碼以獲得更好的性能嗎？"
    },
    {
      "word": "troubleshoot",
      "pos": "v.",
      "meaning": "故障排除、檢修（問題）",
      "example": "I spent all morning trying to troubleshoot the network issue.",
      "example_zh": "我花了一整個早上試圖排除網路問題。"
    },
    {
      "word": "prototype",
      "pos": "n.",
      "meaning": "原型、樣品（產品或模型）",
      "example": "Let's build a quick prototype to test this idea.",
      "example_zh": "我們來快速做個原型來測試這個想法吧。"
    },
    {
      "word": "collaborate",
      "pos": "v.",
      "meaning": "合作、協作（與他人共同工作）",
      "example": "We often collaborate with other teams on big projects.",
      "example_zh": "我們經常在大型專案上與其他團隊合作。"
    },
    {
      "word": "deadline",
      "pos": "n.",
      "meaning": "截止日期、最後期限",
      "example": "The deadline for this task is end of day Friday.",
      "example_zh": "這項任務的截止日期是週五下班前。"
    },
    {
      "word": "feedback",
      "pos": "n.",
      "meaning": "回饋、意見（對某事的反應）",
      "example": "I'd appreciate your feedback on my presentation.",
      "example_zh": "我會很感謝你對我簡報的回饋意見。"
    },
    {
      "word": "innovative",
      "pos": "adj.",
      "meaning": "創新的、革新的（有新意或獨特的）",
      "example": "This new AI tool has some truly innovative features.",
      "example_zh": "這個新的AI工具擁有一些真正創新的功能。"
    },
    {
      "word": "efficient",
      "pos": "adj.",
      "meaning": "高效的、有效率的（資源利用好）",
      "example": "We need a more efficient way to manage our data.",
      "example_zh": "我們需要一個更有效率的方式來管理我們的資料。"
    },
    {
      "word": "update",
      "pos": "v./n.",
      "meaning": "更新、最新消息（使更現代或提供新資訊）",
      "example": "Did you update the software to the latest version?",
      "example_zh": "你有把軟體更新到最新版本嗎？"
    }
  ],
  "english_grammar": [
    {
      "title": "條件句 (If-clauses) 類型一",
      "rule": "用來描述未來可能發生的事情及其結果，假設情況真實，結構為If + S + V(現在簡單式), S + will + V(原形)。",
      "examples": [
        "If you finish the report, we will go for coffee. (如果你寫完報告，我們就去喝咖啡。)",
        "If the system crashes, I will restart it immediately. (如果系統當機，我會立刻重啟。)",
        "If he needs help with the code, just ask me. (如果他需要程式碼的幫助，儘管問我。)"
      ]
    },
    {
      "title": "動名詞 (Gerunds) 作為主詞/受詞",
      "rule": "動詞加-ing變成名詞，可在句中作主詞或受詞，表示行為或活動，使句子更生動自然。",
      "examples": [
        "Debugging code can be really challenging sometimes. (偵錯程式碼有時候真的很具挑戰性。)",
        "I enjoy learning new programming languages in my free time. (我喜歡在空閒時間學習新的程式語言。)",
        "Meeting project deadlines is always important for our team. (達成專案期限對我們團隊來說總是重要的。)"
      ]
    }
  ],
  "japanese_words": [
    {
      "kana": "おきます",
      "kanji_romaji": "起きます / okimasu",
      "meaning": "起床",
      "example": "わたしは まいにち ろくじに おきます。",
      "example_zh": "我每天六點起床。"
    },
    {
      "kana": "たべます",
      "kanji_romaji": "食べます / tabemasu",
      "meaning": "吃",
      "example": "あさごはんを たべます。",
      "example_zh": "吃早餐。"
    },
    {
      "kana": "はたらきます",
      "kanji_romaji": "働きます / hatarakimasu",
      "meaning": "工作",
      "example": "エンジニアとして はたらきます。",
      "example_zh": "當工程師工作。"
    },
    {
      "kana": "やすみます",
      "kanji_romaji": "休みます / yasumimasu",
      "meaning": "休息",
      "example": "きょうは かいしゃを やすみます。",
      "example_zh": "今天公司休息。"
    },
    {
      "kana": "わかります",
      "kanji_romaji": "分かります / wakarimasu",
      "meaning": "懂、明白",
      "example": "にほんごが すこし わかります。",
      "example_zh": "我懂一點日文。"
    },
    {
      "kana": "かいしゃ",
      "kanji_romaji": "会社 / kaisha",
      "meaning": "公司",
      "example": "あなたの かいしゃは どこですか。",
      "example_zh": "你的公司在哪裡？"
    },
    {
      "kana": "しごと",
      "kanji_romaji": "仕事 / shigoto",
      "meaning": "工作",
      "example": "これは たいへんな しごとです。",
      "example_zh": "這是辛苦的工作。"
    },
    {
      "kana": "じかん",
      "kanji_romaji": "時間 / jikan",
      "meaning": "時間",
      "example": "じかんが ありません。",
      "example_zh": "沒有時間。"
    },
    {
      "kana": "えき",
      "kanji_romaji": "駅 / eki",
      "meaning": "車站",
      "example": "えきは ここから ちかいですか。",
      "example_zh": "車站離這裡近嗎？"
    },
    {
      "kana": "パソコン",
      "kanji_romaji": "パソコン / pasokon",
      "meaning": "個人電腦 (PC)",
      "example": "まいにち パソコンを つかいます。",
      "example_zh": "我每天使用電腦。"
    }
  ],
  "japanese_grammar": [
    {
      "title": "名詞 + は + 名詞 + です",
      "structure": "名詞１ + は + 名詞２ + です",
      "rule": "用來介紹事物或說明其性質，名詞1是主題，名詞2是描述，是最基礎的肯定句型。",
      "examples": [
        "わたしは エンジニアです。(我是工程師。)",
        "これは わたしの パソコンです。(這是我的電腦。)"
      ]
    },
    {
      "title": "名詞 + を + 動詞(ます)",
      "structure": "名詞 + を + 動詞(ます形)",
      "rule": "助詞「を」表示動詞的直接受詞，說明動詞作用的對象，構成動詞句的基本形式。",
      "examples": [
        "コーヒーを のみます。(喝咖啡。)",
        "ほんを よみます。(讀書。)"
      ]
    }
  ]
}